Workbook

Sheet Panduan
B2: Database Buyer Briket Shisha (Tempurung Kelapa): Timur Tengah
B3: Disusun 15 Okt 2026 dari sumber publik. Tiap baris punya link sumber. Verifikasi buyer sebelum mengirim harga atau sampel.
B5: CARA PAKAI
B6: 1. Database Buyer | C6: Daftar calon buyer. Isi kolom kuning (PIC, Email, Telepon, Status, Follow-up, Catatan) setelah Anda cek website atau listing-nya.
B7: 2. Sumber Lead | C7: Platform B2B, data impor, dan jalur pemerintah untuk menambah buyer baru. Buyer baru tinggal ditambahkan di baris kosong Database Buyer.
B8: 3. Template Email | C8: Draft email/WhatsApp penawaran dalam bahasa Inggris. Ganti teks [DALAM KURUNG] dengan data Anda.
B9: 4. Penawaran | C9: Log quotation. Ketik ID Buyer, lalu nama dan negara terisi otomatis. Nilai USD & IDR dihitung rumus.
B10: 5. Ringkasan | C10: Rekap otomatis per negara. Jangan diketik manual.
B11: 6. Syarat Ekspor | C11: Checklist dokumen ekspor briket ke Timur Tengah.
B13: KODE WARNA
B14: Sel kuning | C14: Input Anda (boleh diketik/diubah)
B15: Teks biru | C15: Angka asumsi yang diinput manual (mis. kurs)
B16: Teks hitam | C16: Rumus: jangan ditimpa
B18: PRIORITAS (penilaian awal)
B19: A | C19: Terbukti impor/menjual briket kelapa shisha (data kiriman bea cukai atau katalog produk)
B20: B | C20: Trader/distributor arang atau shisha, atau pernah memasang permintaan beli: kandidat kuat
B21: C | C21: Informasi terbatas atau bisa jadi pesaing (juga menjual): prospek sekunder
B23: PENGATURAN
B24: Kurs USD → IDR | C24: 16500
B25: Isi 1 kontainer 20ft (ton) | C25: 18
B27: CATATAN PENTING
B28: Kontak | C28: Kontak pribadi dari papan lead tidak disalin. Buka link Sumber, lalu hubungi lewat formulir/kontak resmi perusahaan. Tidak ada data yang dikarang.
B29: Pesaing | C29: Banyak hasil pencarian adalah pabrik Indonesia (pesaing Anda), jadi tidak dimasukkan sebagai buyer.
B30: Iraq | C30: Ada permintaan aktif (mis. 28 ton per 2 minggu, CIF Umm Qasr, LC) di ExportHub & Go4WorldBusiness, tapi nama perusahaannya tidak tampil. Lihat sheet Sumber Lead.
B31: Waktu | C31: Permintaan shisha naik menjelang Ramadan (perkiraan mulai pertengahan Feb 2027). Kirim penawaran Okt–Des 2026 supaya kontainer tiba tepat waktu (transit 25–45 hari).

Sheet Database Buyer
A1: DATABASE BUYER BRIKET SHISHA: TIMUR TENGAH
A2: ID | B2: Perusahaan | C2: Negara | D2: Kota | E2: Tipe | F2: Prioritas | G2: Produk / Fokus | H2: Website / Listing | I2: PIC | J2: Email | K2: Telepon | L2: Status | M2: Follow-up Berikutnya | N2: Relevansi (hasil riset) | O2: Sumber | P2: Catatan Anda
A3: B001 | B3: Al Sultan Coal & Firewood Trading | C3: UAE | D3: Dubai | E3: Distributor | F3: A | G3: Arang shisha kelapa, arang kayu, briket | H3: https://alsultancoal.com/ | L3: Baru | N3: Menjual coconut shisha charcoal & briket di Dubai; perlu pasokan rutin | O3: https://alsultancoal.com/best-coconut-charcoal-dubai/
A4: B002 | B4: Soex (distributor shisha) | C4: UAE | D4: Dubai | E4: Distributor | F4: B | G4: Perisa shisha + arang kelapa (merek Irfaz Coco-Zeal) | H4: https://soex.com/ | L4: Baru | N4: Grosir arang kelapa ke Dubai, Sharjah, Abu Dhabi; peluang private label | O4: https://soex.com/afzal-wholesale-supplier-distributor-of-shisha-flavors-in-united-arab-emirates/
A5: B003 | B5: Al Fakher | C5: UAE | D5: Ajman | E5: Brand | F5: B | G5: Brand shisha besar; menjual arang kelapa kubus | H5: https://alfakher.com/ | L5: Baru | N5: Brand global; sasaran OEM/maklon jangka panjang (seleksi ketat, butuh sertifikat lengkap) | O5: https://hookah.com/c/hookah-charcoal
A6: B004 | B6: Context General Trading LLC | C6: UAE | D6: Dubai (Deira) | E6: Trader | F6: B | G6: Arang tempurung kelapa untuk hookah | H6: https://www.go4worldbusiness.com/suppliers/united-arab-emirates/charcoal.html | L6: Baru | N6: Terdaftar di direktori UAE sebagai pemasok coconut shell hookah charcoal | O6: https://www.go4worldbusiness.com/suppliers/united-arab-emirates/charcoal.html
A7: B005 | B7: Aristo General Trading F.Z.E | C7: UAE | D7: Ajman | E7: Trader | F7: B | G7: Arang shisha | H7: https://www.go4worldbusiness.com/suppliers/united-arab-emirates/charcoal.html | L7: Baru | N7: Terdaftar untuk shisha charcoal (MOQ 400 menurut listing) | O7: https://www.go4worldbusiness.com/suppliers/united-arab-emirates/charcoal.html
A8: B006 | B8: N I R A N Coal & Firewood Trading | C8: UAE | D8: Dubai | E8: Trader | F8: B | G8: Arang kelapa, arang kayu, arang shisha | H8: https://www.go4worldbusiness.com/suppliers/united-arab-emirates/dubai/wood-charcoal.html | L8: Baru | N8: Menjual coconut shell & shisha charcoal, ada layanan re-ekspor | O8: https://www.go4worldbusiness.com/suppliers/united-arab-emirates/dubai/wood-charcoal.html
A9: B007 | B9: Jas General Trading | C9: UAE | D9: Dubai | E9: Trader | F9: C | G9: Arang tempurung kelapa | H9: https://www.go4worldbusiness.com/suppliers/united-arab-emirates/dubai/wood-charcoal.html | L9: Baru | N9: Listing direktori; info terbatas | O9: https://www.go4worldbusiness.com/suppliers/united-arab-emirates/dubai/wood-charcoal.html
A10: B008 | B10: CocoSham Co. (ShamBuy KSA) | C10: Saudi Arabia | D10: Jeddah | E10: Wholesaler | F10: B | G10: Shisha, perlengkapan BBQ, arang grosir & eceran | H10: https://shambuy.sa/en/charcoal-wholesale/c717263282 | L10: Baru | N10: Usaha lokal Jeddah yang menjual arang grosir; cocok untuk 1 kontainer campur | O10: https://shambuy.sa/en/charcoal-wholesale/c717263282
A11: B009 | B11: Superior Coco (Superiorcoco Coals) | C11: Jordan | D11: Amman | E11: Wholesaler | F11: A | G11: Briket arang, arang hookah, arang kelapa | H11: https://www.go4worldbusiness.com/suppliers/jordan/charcoal.html | L11: Baru | N11: Grosir arang kelapa dengan lini arang hookah di Amman | O11: https://www.go4worldbusiness.com/suppliers/jordan/charcoal.html
A12: B010 | B12: Jordanian Company For Natural Coal Manufacturing | C12: Jordan | D12: Amman | E12: Distributor | F12: B | G12: Dealer arang, termasuk arang shisha | H12: https://www.go4worldbusiness.com/member/view/3071365/jordanian-company-for-natural-coal-manufacturing.html | L12: Baru | N12: Terdaftar sebagai buyer sekaligus penjual; ada layanan ekspor | O12: https://www.go4worldbusiness.com/member/view/3071365/jordanian-company-for-natural-coal-manufacturing.html
A13: B011 | B13: Briqo | C13: Jordan | D13: Amman | E13: Trader | F13: C | G13: Briket kelapa shisha (bahan baku Afrika) | H13: https://www.go4worldbusiness.com/suppliers/jordan/charcoal.html | L13: Baru | N13: Saat ini pakai tempurung Afrika, kirim FOB Mesir; bisa jadi pesaing atau buyer alternatif | O13: https://www.go4worldbusiness.com/suppliers/jordan/charcoal.html
A14: B012 | B14: Arnaout Trading Company | C14: Lebanon | D14: Beirut | E14: Importir | F14: B | G14: Arang hookah / arang kelapa | H14: https://importer.tradekey.com/lebanon/hookah-charcoal.htm | L14: Baru | N14: Memasang permintaan beli arang hookah di Tradekey | O14: https://importer.tradekey.com/lebanon/hookah-charcoal.htm
... A19: B017 | B19: Khairy Group | C19: Egypt | D19: Giza | E19: Trader | F19: C | G19: Briket tempurung kelapa (shisha charcoal) | H19: https://www.go4worldbusiness.com/suppliers/egypt/coconut-shell-charcoal.html | L19: Baru | N19: Importir & eksportir sekaligus; bisa beli bahan jadi untuk dikemas ulang | O19: https://www.go4worldbusiness.com/suppliers/egypt/coconut-shell-charcoal.html
A20: B018
A21: B019
A22: B020
A23: B021
A24: B022
A25: B023
A26: B024
A27: B025
A28: B026
A29: B027
A30: B028
A31: B029
... A202: B200

Sheet Sumber Lead
A1: SUMBER LEAD: CARA MENAMBAH BUYER BARU
A2: Sumber | B2: Jenis | C2: Pasar | D2: Temuan / Cara pakai | E2: Link | F2: Sudah Dicek?
A3: Tradewheel | B3: Papan permintaan beli | C3: Saudi Arabia | D3: Ada permintaan importir Riyadh untuk arang shisha grade 1 dan pedagang grosir yang cari pasokan. Cek tanggal posting. | E3: https://www.tradewheel.com/buyers/shisha-charcoal/saudi-arabia/ | F3: Belum
A4: ExportHub: Iraq | B4: Papan permintaan beli | C4: Iraq | D4: Buyer Iraq cari pabrik briket kelapa untuk lini hookah; salah satunya minta 28 ton per 2 minggu. | E4: https://www.exporthub.com/iraq/charcoal-importers/ | F4: Belum
A5: ExportHub: Hookah Coconut | B5: Papan permintaan beli | C5: Global | D5: Daftar importir hookah coconut shell charcoal lintas negara. | E5: https://www.exporthub.com/importers/hookah-coconut-shell-charcoal/ | F5: Belum
A6: Go4WorldBusiness: Iraq | B6: Papan permintaan beli | C6: Iraq | D6: Permintaan kontainer penuh CIF Umm Qasr dengan pembayaran LC. | E6: https://www.go4worldbusiness.com/buyers/iraq/charcoal.html | F6: Belum
A7: Go4WorldBusiness: Jordan | B7: Papan permintaan beli | C7: Jordan | D7: Daftar buyer briket arang di Yordania. | E7: https://www.go4worldbusiness.com/buyers/jordan/charcoal-briquettes.html | F7: Belum
A8: Tradekey: Lebanon | B8: Papan permintaan beli | C8: Lebanon | D8: Buyer arang hookah Lebanon terbaru. | E8: https://importer.tradekey.com/lebanon/hookah-charcoal.htm | F8: Belum
A9: EC21: Lebanon | B9: Papan permintaan beli | C9: Lebanon/Iraq | D9: Lead lama (sebagian dari 2014). Pakai hanya sebagai nama perusahaan untuk dicek ulang. | E9: https://importer.ec21.com/LB/Charcoal--1101.html?isGroupList=N | F9: Belum
A10: Volza | B10: Data impor bea cukai | C10: Egypt + negara lain | D10: 21 importir briket arang di Mesir, lengkap dengan tanggal & volume kiriman. Bisa filter negara lain (berbayar untuk detail). | E10: https://www.volza.com/p/charcoal-briquettes/buyers/buyers-in-egypt/ | F10: Belum
A11: Haran Resources | B11: Papan permintaan beli | C11: Saudi / UAE | D11: Permintaan arang tempurung kelapa & hookah dari Saudi dan UAE (tanpa tanggal). | E11: https://www.haranresources.com/charcoal.html | F11: Belum
A12: Inaexport (Kemendag) | B12: Pemerintah RI | C12: Global | D12: Daftarkan produk Anda; buyer luar negeri yang terverifikasi Kemendag bisa mengirim inquiry. Gratis. | E12: https://inaexport.id/ | F12: Belum
A13: ITPC Dubai & ITPC Jeddah | B13: Pemerintah RI | C13: UAE / Saudi | D13: Pusat promosi dagang RI. Minta dicarikan buyer dan dijadwalkan business matching (online/offline). | E13: https://inaexport.id/ | F13: Belum
A14: Trade Expo Indonesia (TEI) | B14: Pameran | C14: Global | D14: Pameran tahunan (biasanya Oktober) di BSD; banyak buyer Timur Tengah datang. Siapkan sampel & katalog. | E14: https://tradeexpoindonesia.com/ | F14: Belum

Sheet Template Email
B2: TEMPLATE EMAIL & WHATSAPP PENAWARAN
B3: Ganti semua teks [DALAM KURUNG]. Spesifikasi diisi dari hasil uji lab Anda sendiri, jangan pakai angka contoh.
B6: 1. Email perkenalan
B7: Subject | C7: Indonesian Coconut Shisha Charcoal: Direct Factory Supply for [COMPANY NAME]
B8: Body | C8: Dear [Mr./Ms. NAME / Purchasing Team], I hope this message finds you well. My name is [YOUR NAME] from [YOUR COMPANY], a coconut shell charcoal briquette producer based in [CITY], Indonesia. We noticed that [COMPANY NAME] supplies shisha charcoal in [COUNTRY/CITY], and we would like to offer you a reliable, direct-from-factory source. Product specification (lab-tested): • Raw material: 100% coconut shell charcoal, [binder: tapioca] • Shape & size: cube [25 x 25 x 25 mm] (other sizes available) • Ash content: [≤ 2.5%] | Ash colour: [white/light grey] • Moisture: [≤ 6%] | Fixed carbon: [≥ 75%] • Burning time: [≥ 90 minutes] | No smell, no sparks, no chemicals • Packing: [1 kg inner box / 10 kg master carton] or private label • Capacity: [1–3] x 20ft container per month (approx. 18 tons per 20ft) Commercial terms: • Price: USD [PRICE] per ton [FOB Surabaya/Semarang/Jakarta] or [CIF YOUR PORT] on request • MOQ: 1 x 20ft container | Payment: [30% T/T deposit, 70% against B/L copy] or L/C at sight • Lead time: [21–30] days after deposit | Private label & custom packaging available • Documents: COA, MSDS, non-dangerous-goods (self-heating) test, Certificate of Origin We would be happy to send free samples (courier cost [shared / on us]) so you can test the burning quality yourself. May I know your monthly requirement and preferred size, so I can prepare a formal quotation? Best regards, [YOUR NAME] [POSITION] | [YOUR COMPANY] WhatsApp: [+62 ...] | Email: [EMAIL] | Website: [WEBSITE]
B10: 2. Follow-up (hari ke-4)
B11: Subject | C11: Re: Indonesian Coconut Shisha Charcoal: Free Samples for [COMPANY NAME]
B12: Body | C12: Dear [NAME], I am following up on my previous email about our coconut shisha charcoal. I have attached our product photos and lab test report for your reference. Many of our buyers start with one mixed container (e.g., 25 mm and 26 mm cubes) to test the market. We can also pack under your own brand. Would you like us to send samples this week? Please share your delivery address and the contact person. Best regards, [YOUR NAME]
B14: 3. Follow-up terakhir (hari ke-10)
B15: Subject | C15: Ramadan 2027 stock: shisha charcoal booking for [COMPANY NAME]
B16: Body | C16: Dear [NAME], Ramadan season is the peak period for shisha charcoal. With 25–45 days shipping time to [COUNTRY], orders confirmed before [DATE, e.g. 15 December 2026] will arrive in time for the season. We still have production slots available for [MONTH]. If now is not the right time, could you let me know who handles purchasing, or when I may contact you again? Thank you for your time. Best regards, [YOUR NAME]
B18: 4. WhatsApp singkat
B19: Pesan | C19: Assalamu'alaikum [NAME], this is [YOUR NAME] from [YOUR COMPANY], Indonesia. We produce 100% coconut shell shisha charcoal (ash ≤ [2.5]%, burning ≥ [90] min), capacity [1–3] containers/month, private label available. May I send you our price list and free samples? Thank you 🙏
B21: 5. Balasan minta harga
B22: Body | C22: Dear [NAME], Thank you for your interest. Please find our quotation below: • Product: Coconut shisha charcoal cube [SIZE] • Quantity: [X] x 20ft container ([X] tons) • Price: USD [PRICE]/ton [INCOTERM + PORT] • Packing: [DETAIL] • Payment: [TERMS] • Delivery: [X] days after deposit • Validity: [14] days Proforma invoice will be issued upon your confirmation. Best regards, [YOUR NAME]
B24: TIPS
C25: • Kirim email pagi waktu Timur Tengah (UTC+3/+4), kira-kira pukul 13.00–15.00 WIB, Minggu–Kamis.
C26: • Banyak buyer Timur Tengah lebih cepat membalas di WhatsApp; kirim WA setelah email pertama.
C27: • Lampirkan foto produk (uji bakar & warna abu) dan hasil lab. Ini lebih meyakinkan daripada deskripsi panjang.
C28: • Jangan kirim harga final sebelum tahu volume, ukuran, dan pelabuhan tujuan buyer.
C29: • Catat setiap kiriman di Database Buyer (Status + tanggal Follow-up). Tanggal yang sudah lewat otomatis berwarna merah.

Sheet Penawaran
A1: CATATAN PENAWARAN HARGA
A2: No. Penawaran | B2: Tanggal | C2: ID Buyer | D2: Perusahaan | E2: Negara | F2: Incoterm | G2: Pelabuhan Tujuan | H2: Ukuran | I2: Jml Kontainer 20ft | J2: Volume (ton) | K2: Harga (USD/ton) | L2: Nilai (USD) | M2: Nilai (IDR) | N2: Berlaku s/d | O2: Status | P2: Catatan
A3: QT-2026-001 | B3: 46310 | C3: B001 | D3: =IF(C3="","",IFERROR(INDEX('Database Buyer'!$B$3:$B$202,MATCH(C3,'Database Buyer'!$A$3:$A$202,0)),"ID tidak ditemukan")) | E3: =IF(C3="","",IFERROR(INDEX('Database Buyer'!$C$3:$C$202,MATCH(C3,'Database Buyer'!$A$3:$A$202,0)),"")) | F3: CIF | G3: Jebel Ali | H3: 25 mm | I3: 1 | J3: =IF(I3="","",I3*Panduan!$C$25) | K3: 1100 | L3: =IF(OR(J3="",K3=""),"",J3*K3) | M3: =IF(L3="","",L3*Panduan!$C$24) | N3: 46324 | O3: Draft | P3: CONTOH: ganti/hapus baris ini. Harga ilustrasi, bukan harga pasar.
D4: =IF(C4="","",IFERROR(INDEX('Database Buyer'!$B$3:$B$202,MATCH(C4,'Database Buyer'!$A$3:$A$202,0)),"ID tidak ditemukan")) | E4: =IF(C4="","",IFERROR(INDEX('Database Buyer'!$C$3:$C$202,MATCH(C4,'Database Buyer'!$A$3:$A$202,0)),"")) | J4: =IF(I4="","",I4*Panduan!$C$25) | L4: =IF(OR(J4="",K4=""),"",J4*K4) | M4: =IF(L4="","",L4*Panduan!$C$24)
D5: =IF(C5="","",IFERROR(INDEX('Database Buyer'!$B$3:$B$202,MATCH(C5,'Database Buyer'!$A$3:$A$202,0)),"ID tidak ditemukan")) | E5: =IF(C5="","",IFERROR(INDEX('Database Buyer'!$C$3:$C$202,MATCH(C5,'Database Buyer'!$A$3:$A$202,0)),"")) | J5: =IF(I5="","",I5*Panduan!$C$25) | L5: =IF(OR(J5="",K5=""),"",J5*K5) | M5: =IF(L5="","",L5*Panduan!$C$24)
D6: =IF(C6="","",IFERROR(INDEX('Database Buyer'!$B$3:$B$202,MATCH(C6,'Database Buyer'!$A$3:$A$202,0)),"ID tidak ditemukan")) | E6: =IF(C6="","",IFERROR(INDEX('Database Buyer'!$C$3:$C$202,MATCH(C6,'Database Buyer'!$A$3:$A$202,0)),"")) | J6: =IF(I6="","",I6*Panduan!$C$25) | L6: =IF(OR(J6="",K6=""),"",J6*K6) | M6: =IF(L6="","",L6*Panduan!$C$24)
D7: =IF(C7="","",IFERROR(INDEX('Database Buyer'!$B$3:$B$202,MATCH(C7,'Database Buyer'!$A$3:$A$202,0)),"ID tidak ditemukan")) | E7: =IF(C7="","",IFERROR(INDEX('Database Buyer'!$C$3:$C$202,MATCH(C7,'Database Buyer'!$A$3:$A$202,0)),"")) | J7: =IF(I7="","",I7*Panduan!$C$25) | L7: =IF(OR(J7="",K7=""),"",J7*K7) | M7: =IF(L7="","",L7*Panduan!$C$24)
D8: =IF(C8="","",IFERROR(INDEX('Database Buyer'!$B$3:$B$202,MATCH(C8,'Database Buyer'!$A$3:$A$202,0)),"ID tidak ditemukan")) | E8: =IF(C8="","",IFERROR(INDEX('Database Buyer'!$C$3:$C$202,MATCH(C8,'Database Buyer'!$A$3:$A$202,0)),"")) | J8: =IF(I8="","",I8*Panduan!$C$25) | L8: =IF(OR(J8="",K8=""),"",J8*K8) | M8: =IF(L8="","",L8*Panduan!$C$24)
D9: =IF(C9="","",IFERROR(INDEX('Database Buyer'!$B$3:$B$202,MATCH(C9,'Database Buyer'!$A$3:$A$202,0)),"ID tidak ditemukan")) | E9: =IF(C9="","",IFERROR(INDEX('Database Buyer'!$C$3:$C$202,MATCH(C9,'Database Buyer'!$A$3:$A$202,0)),"")) | J9: =IF(I9="","",I9*Panduan!$C$25) | L9: =IF(OR(J9="",K9=""),"",J9*K9) | M9: =IF(L9="","",L9*Panduan!$C$24)
D10: =IF(C10="","",IFERROR(INDEX('Database Buyer'!$B$3:$B$202,MATCH(C10,'Database Buyer'!$A$3:$A$202,0)),"ID tidak ditemukan")) | E10: =IF(C10="","",IFERROR(INDEX('Database Buyer'!$C$3:$C$202,MATCH(C10,'Database Buyer'!$A$3:$A$202,0)),"")) | J10: =IF(I10="","",I10*Panduan!$C$25) | L10: =IF(OR(J10="",K10=""),"",J10*K10) | M10: =IF(L10="","",L10*Panduan!$C$24)
D11: =IF(C11="","",IFERROR(INDEX('Database Buyer'!$B$3:$B$202,MATCH(C11,'Database Buyer'!$A$3:$A$202,0)),"ID tidak ditemukan")) | E11: =IF(C11="","",IFERROR(INDEX('Database Buyer'!$C$3:$C$202,MATCH(C11,'Database Buyer'!$A$3:$A$202,0)),"")) | J11: =IF(I11="","",I11*Panduan!$C$25) | L11: =IF(OR(J11="",K11=""),"",J11*K11) | M11: =IF(L11="","",L11*Panduan!$C$24)
D12: =IF(C12="","",IFERROR(INDEX('Database Buyer'!$B$3:$B$202,MATCH(C12,'Database Buyer'!$A$3:$A$202,0)),"ID tidak ditemukan")) | E12: =IF(C12="","",IFERROR(INDEX('Database Buyer'!$C$3:$C$202,MATCH(C12,'Database Buyer'!$A$3:$A$202,0)),"")) | J12: =IF(I12="","",I12*Panduan!$C$25) | L12: =IF(OR(J12="",K12=""),"",J12*K12) | M12: =IF(L12="","",L12*Panduan!$C$24)
D13: =IF(C13="","",IFERROR(INDEX('Database Buyer'!$B$3:$B$202,MATCH(C13,'Database Buyer'!$A$3:$A$202,0)),"ID tidak ditemukan")) | E13: =IF(C13="","",IFERROR(INDEX('Database Buyer'!$C$3:$C$202,MATCH(C13,'Database Buyer'!$A$3:$A$202,0)),"")) | J13: =IF(I13="","",I13*Panduan!$C$25) | L13: =IF(OR(J13="",K13=""),"",J13*K13) | M13: =IF(L13="","",L13*Panduan!$C$24)
D14: =IF(C14="","",IFERROR(INDEX('Database Buyer'!$B$3:$B$202,MATCH(C14,'Database Buyer'!$A$3:$A$202,0)),"ID tidak ditemukan")) | E14: =IF(C14="","",IFERROR(INDEX('Database Buyer'!$C$3:$C$202,MATCH(C14,'Database Buyer'!$A$3:$A$202,0)),"")) | J14: =IF(I14="","",I14*Panduan!$C$25) | L14: =IF(OR(J14="",K14=""),"",J14*K14) | M14: =IF(L14="","",L14*Panduan!$C$24)
D15: =IF(C15="","",IFERROR(INDEX('Database Buyer'!$B$3:$B$202,MATCH(C15,'Database Buyer'!$A$3:$A$202,0)),"ID tidak ditemukan")) | E15: =IF(C15="","",IFERROR(INDEX('Database Buyer'!$C$3:$C$202,MATCH(C15,'Database Buyer'!$A$3:$A$202,0)),"")) | J15: =IF(I15="","",I15*Panduan!$C$25) | L15: =IF(OR(J15="",K15=""),"",J15*K15) | M15: =IF(L15="","",L15*Panduan!$C$24)
... D202: =IF(C202="","",IFERROR(INDEX('Database Buyer'!$B$3:$B$202,MATCH(C202,'Database Buyer'!$A$3:$A$202,0)),"ID tidak ditemukan")) | E202: =IF(C202="","",IFERROR(INDEX('Database Buyer'!$C$3:$C$202,MATCH(C202,'Database Buyer'!$A$3:$A$202,0)),"")) | J202: =IF(I202="","",I202*Panduan!$C$25) | L202: =IF(OR(J202="",K202=""),"",J202*K202) | M202: =IF(L202="","",L202*Panduan!$C$24)

Sheet Ringkasan
B2: RINGKASAN
B4: Negara | C4: Jml Buyer | D4: Prior. A | E4: Prior. B | F4: Prior. C | G4: Sudah Kontak | H4: Deal | I4: Penawaran (USD) | J4: Diterima (USD)
B5: UAE | C5: =COUNTIF('Database Buyer'!$C$3:$C$202,$B5) | D5: =COUNTIFS('Database Buyer'!$C$3:$C$202,$B5,'Database Buyer'!$F$3:$F$202,"A") | E5: =COUNTIFS('Database Buyer'!$C$3:$C$202,$B5,'Database Buyer'!$F$3:$F$202,"B") | F5: =COUNTIFS('Database Buyer'!$C$3:$C$202,$B5,'Database Buyer'!$F$3:$F$202,"C") | G5: =C5-COUNTIFS('Database Buyer'!$C$3:$C$202,$B5,'Database Buyer'!$L$3:$L$202,"Baru") | H5: =COUNTIFS('Database Buyer'!$C$3:$C$202,$B5,'Database Buyer'!$L$3:$L$202,"Deal") | I5: =SUMIFS(Penawaran!$L$3:$L$202,Penawaran!$E$3:$E$202,$B5) | J5: =SUMIFS(Penawaran!$L$3:$L$202,Penawaran!$E$3:$E$202,$B5,Penawaran!$O$3:$O$202,"Diterima")
B6: Saudi Arabia | C6: =COUNTIF('Database Buyer'!$C$3:$C$202,$B6) | D6: =COUNTIFS('Database Buyer'!$C$3:$C$202,$B6,'Database Buyer'!$F$3:$F$202,"A") | E6: =COUNTIFS('Database Buyer'!$C$3:$C$202,$B6,'Database Buyer'!$F$3:$F$202,"B") | F6: =COUNTIFS('Database Buyer'!$C$3:$C$202,$B6,'Database Buyer'!$F$3:$F$202,"C") | G6: =C6-COUNTIFS('Database Buyer'!$C$3:$C$202,$B6,'Database Buyer'!$L$3:$L$202,"Baru") | H6: =COUNTIFS('Database Buyer'!$C$3:$C$202,$B6,'Database Buyer'!$L$3:$L$202,"Deal") | I6: =SUMIFS(Penawaran!$L$3:$L$202,Penawaran!$E$3:$E$202,$B6) | J6: =SUMIFS(Penawaran!$L$3:$L$202,Penawaran!$E$3:$E$202,$B6,Penawaran!$O$3:$O$202,"Diterima")
B7: Jordan | C7: =COUNTIF('Database Buyer'!$C$3:$C$202,$B7) | D7: =COUNTIFS('Database Buyer'!$C$3:$C$202,$B7,'Database Buyer'!$F$3:$F$202,"A") | E7: =COUNTIFS('Database Buyer'!$C$3:$C$202,$B7,'Database Buyer'!$F$3:$F$202,"B") | F7: =COUNTIFS('Database Buyer'!$C$3:$C$202,$B7,'Database Buyer'!$F$3:$F$202,"C") | G7: =C7-COUNTIFS('Database Buyer'!$C$3:$C$202,$B7,'Database Buyer'!$L$3:$L$202,"Baru") | H7: =COUNTIFS('Database Buyer'!$C$3:$C$202,$B7,'Database Buyer'!$L$3:$L$202,"Deal") | I7: =SUMIFS(Penawaran!$L$3:$L$202,Penawaran!$E$3:$E$202,$B7) | J7: =SUMIFS(Penawaran!$L$3:$L$202,Penawaran!$E$3:$E$202,$B7,Penawaran!$O$3:$O$202,"Diterima")
B8: Lebanon | C8: =COUNTIF('Database Buyer'!$C$3:$C$202,$B8) | D8: =COUNTIFS('Database Buyer'!$C$3:$C$202,$B8,'Database Buyer'!$F$3:$F$202,"A") | E8: =COUNTIFS('Database Buyer'!$C$3:$C$202,$B8,'Database Buyer'!$F$3:$F$202,"B") | F8: =COUNTIFS('Database Buyer'!$C$3:$C$202,$B8,'Database Buyer'!$F$3:$F$202,"C") | G8: =C8-COUNTIFS('Database Buyer'!$C$3:$C$202,$B8,'Database Buyer'!$L$3:$L$202,"Baru") | H8: =COUNTIFS('Database Buyer'!$C$3:$C$202,$B8,'Database Buyer'!$L$3:$L$202,"Deal") | I8: =SUMIFS(Penawaran!$L$3:$L$202,Penawaran!$E$3:$E$202,$B8) | J8: =SUMIFS(Penawaran!$L$3:$L$202,Penawaran!$E$3:$E$202,$B8,Penawaran!$O$3:$O$202,"Diterima")
B9: Egypt | C9: =COUNTIF('Database Buyer'!$C$3:$C$202,$B9) | D9: =COUNTIFS('Database Buyer'!$C$3:$C$202,$B9,'Database Buyer'!$F$3:$F$202,"A") | E9: =COUNTIFS('Database Buyer'!$C$3:$C$202,$B9,'Database Buyer'!$F$3:$F$202,"B") | F9: =COUNTIFS('Database Buyer'!$C$3:$C$202,$B9,'Database Buyer'!$F$3:$F$202,"C") | G9: =C9-COUNTIFS('Database Buyer'!$C$3:$C$202,$B9,'Database Buyer'!$L$3:$L$202,"Baru") | H9: =COUNTIFS('Database Buyer'!$C$3:$C$202,$B9,'Database Buyer'!$L$3:$L$202,"Deal") | I9: =SUMIFS(Penawaran!$L$3:$L$202,Penawaran!$E$3:$E$202,$B9) | J9: =SUMIFS(Penawaran!$L$3:$L$202,Penawaran!$E$3:$E$202,$B9,Penawaran!$O$3:$O$202,"Diterima")
B10: Iraq | C10: =COUNTIF('Database Buyer'!$C$3:$C$202,$B10) | D10: =COUNTIFS('Database Buyer'!$C$3:$C$202,$B10,'Database Buyer'!$F$3:$F$202,"A") | E10: =COUNTIFS('Database Buyer'!$C$3:$C$202,$B10,'Database Buyer'!$F$3:$F$202,"B") | F10: =COUNTIFS('Database Buyer'!$C$3:$C$202,$B10,'Database Buyer'!$F$3:$F$202,"C") | G10: =C10-COUNTIFS('Database Buyer'!$C$3:$C$202,$B10,'Database Buyer'!$L$3:$L$202,"Baru") | H10: =COUNTIFS('Database Buyer'!$C$3:$C$202,$B10,'Database Buyer'!$L$3:$L$202,"Deal") | I10: =SUMIFS(Penawaran!$L$3:$L$202,Penawaran!$E$3:$E$202,$B10) | J10: =SUMIFS(Penawaran!$L$3:$L$202,Penawaran!$E$3:$E$202,$B10,Penawaran!$O$3:$O$202,"Diterima")
B11: Kuwait | C11: =COUNTIF('Database Buyer'!$C$3:$C$202,$B11) | D11: =COUNTIFS('Database Buyer'!$C$3:$C$202,$B11,'Database Buyer'!$F$3:$F$202,"A") | E11: =COUNTIFS('Database Buyer'!$C$3:$C$202,$B11,'Database Buyer'!$F$3:$F$202,"B") | F11: =COUNTIFS('Database Buyer'!$C$3:$C$202,$B11,'Database Buyer'!$F$3:$F$202,"C") | G11: =C11-COUNTIFS('Database Buyer'!$C$3:$C$202,$B11,'Database Buyer'!$L$3:$L$202,"Baru") | H11: =COUNTIFS('Database Buyer'!$C$3:$C$202,$B11,'Database Buyer'!$L$3:$L$202,"Deal") | I11: =SUMIFS(Penawaran!$L$3:$L$202,Penawaran!$E$3:$E$202,$B11) | J11: =SUMIFS(Penawaran!$L$3:$L$202,Penawaran!$E$3:$E$202,$B11,Penawaran!$O$3:$O$202,"Diterima")
B12: Qatar | C12: =COUNTIF('Database Buyer'!$C$3:$C$202,$B12) | D12: =COUNTIFS('Database Buyer'!$C$3:$C$202,$B12,'Database Buyer'!$F$3:$F$202,"A") | E12: =COUNTIFS('Database Buyer'!$C$3:$C$202,$B12,'Database Buyer'!$F$3:$F$202,"B") | F12: =COUNTIFS('Database Buyer'!$C$3:$C$202,$B12,'Database Buyer'!$F$3:$F$202,"C") | G12: =C12-COUNTIFS('Database Buyer'!$C$3:$C$202,$B12,'Database Buyer'!$L$3:$L$202,"Baru") | H12: =COUNTIFS('Database Buyer'!$C$3:$C$202,$B12,'Database Buyer'!$L$3:$L$202,"Deal") | I12: =SUMIFS(Penawaran!$L$3:$L$202,Penawaran!$E$3:$E$202,$B12) | J12: =SUMIFS(Penawaran!$L$3:$L$202,Penawaran!$E$3:$E$202,$B12,Penawaran!$O$3:$O$202,"Diterima")
B13: Oman | C13: =COUNTIF('Database Buyer'!$C$3:$C$202,$B13) | D13: =COUNTIFS('Database Buyer'!$C$3:$C$202,$B13,'Database Buyer'!$F$3:$F$202,"A") | E13: =COUNTIFS('Database Buyer'!$C$3:$C$202,$B13,'Database Buyer'!$F$3:$F$202,"B") | F13: =COUNTIFS('Database Buyer'!$C$3:$C$202,$B13,'Database Buyer'!$F$3:$F$202,"C") | G13: =C13-COUNTIFS('Database Buyer'!$C$3:$C$202,$B13,'Database Buyer'!$L$3:$L$202,"Baru") | H13: =COUNTIFS('Database Buyer'!$C$3:$C$202,$B13,'Database Buyer'!$L$3:$L$202,"Deal") | I13: =SUMIFS(Penawaran!$L$3:$L$202,Penawaran!$E$3:$E$202,$B13) | J13: =SUMIFS(Penawaran!$L$3:$L$202,Penawaran!$E$3:$E$202,$B13,Penawaran!$O$3:$O$202,"Diterima")
B14: Bahrain | C14: =COUNTIF('Database Buyer'!$C$3:$C$202,$B14) | D14: =COUNTIFS('Database Buyer'!$C$3:$C$202,$B14,'Database Buyer'!$F$3:$F$202,"A") | E14: =COUNTIFS('Database Buyer'!$C$3:$C$202,$B14,'Database Buyer'!$F$3:$F$202,"B") | F14: =COUNTIFS('Database Buyer'!$C$3:$C$202,$B14,'Database Buyer'!$F$3:$F$202,"C") | G14: =C14-COUNTIFS('Database Buyer'!$C$3:$C$202,$B14,'Database Buyer'!$L$3:$L$202,"Baru") | H14: =COUNTIFS('Database Buyer'!$C$3:$C$202,$B14,'Database Buyer'!$L$3:$L$202,"Deal") | I14: =SUMIFS(Penawaran!$L$3:$L$202,Penawaran!$E$3:$E$202,$B14) | J14: =SUMIFS(Penawaran!$L$3:$L$202,Penawaran!$E$3:$E$202,$B14,Penawaran!$O$3:$O$202,"Diterima")
B15: TOTAL | C15: =SUM(C5:C14) | D15: =SUM(D5:D14) | E15: =SUM(E5:E14) | F15: =SUM(F5:F14) | G15: =SUM(G5:G14) | H15: =SUM(H5:H14) | I15: =SUM(I5:I14) | J15: =SUM(J5:J14)
B17: Follow-up jatuh tempo (hari ini/lewat): | G17: =COUNTIFS('Database Buyer'!$M$3:$M$202,"<="&TODAY(),'Database Buyer'!$L$3:$L$202,"<>Deal",'Database Buyer'!$L$3:$L$202,"<>Tidak Tertarik")
B18: Iraq, Kuwait, Qatar, Oman, Bahrain belum punya nama buyer terverifikasi; tambahkan dari sheet Sumber Lead.

Sheet Syarat Ekspor
A1: CHECKLIST SYARAT EKSPOR BRIKET SHISHA
A2: Ringkasan umum. Konfirmasi ke forwarder, buyer, dan ITPC karena aturan tiap negara bisa berubah.
A3: Tahap | B3: Persyaratan | C3: Keterangan | D3: Siap? ✓
A4: Legalitas | B4: NIB dengan KBLI yang mencakup ekspor | C4: Daftar lewat OSS; dipakai untuk PEB (Pemberitahuan Ekspor Barang). | D4: Belum
A5: Produk | B5: Kode HS 4402.20 | C5: Arang dari tempurung atau biji. Pastikan forwarder memakai kode yang sama di semua dokumen. | D5: Belum
A6: Produk | B6: Certificate of Analysis (COA) | C6: Uji lab: kadar abu, air, karbon terikat, nilai kalor, waktu bakar. Buyer hampir selalu memintanya. | D6: Belum
A7: Pengiriman | B7: MSDS + uji self-heating (UN Test N.4) | C7: Arang berpotensi dikategorikan barang berbahaya (kelas 4.2). Hasil uji 'non-dangerous' membuat kapal mau menerima muatan. | D7: Belum
A8: Pengiriman | B8: Fumigasi / pengeringan & pendinginan | C8: Briket harus kering dan dingin sebelum dikemas; banyak pelayaran minta surat keterangan suhu. | D8: Belum
A9: Dokumen | B9: Commercial Invoice, Packing List, B/L | C9: Standar ekspor; nama barang & berat harus sama persis di semua dokumen. | D9: Belum
A10: Dokumen | B10: Certificate of Origin (SKA) | C10: Dari instansi penerbit SKA (via e-SKA Kemendag). Dibutuhkan untuk bea masuk di negara tujuan. | D10: Belum
A11: Saudi Arabia | B11: Registrasi produk di platform SABER (SASO) | C11: Biasanya diurus importir; tanyakan apakah mereka butuh sertifikat dari Anda. | D11: Belum
A12: Mesir | B12: Registrasi pabrik di GOEIC (jika diminta) | C12: Beberapa produk konsumen wajib terdaftar; konfirmasi ke importir Mesir. | D12: Belum
A13: Pembayaran | B13: Skema T/T deposit atau L/C at sight | C13: Untuk buyer baru, minta deposit minimal 30% atau L/C dari bank terpercaya. | D13: Belum
